content_ranker/__about__.py
content_ranker/__init__.py
content_ranker/core.py
content_ranker/exceptions.py
content_ranker/features/__init__.py
content_ranker/features/features_for_html.py
content_ranker/models/__init__.py
content_ranker/models/classifiers.py
content_ranker/models/crf.py
content_ranker/models/predict.py
content_ranker/resources/tags.json
content_ranker/utils/__init__.py
content_ranker/utils/color_labeled_htmls.py
content_ranker-0.0.0.dist-info/METADATA
content_ranker-0.0.0.dist-info/WHEEL
content_ranker-0.0.0.dist-info/RECORD
