Metadata-Version: 2.1
Name: content-ranker
Version: 0.0.0
Summary: Content ranking using ZDA model
Project-URL: Documentation, https://github.com/document-analysis/zda-content-ranker#readme
Project-URL: Issues, https://github.com/document-analysis/zda-content-ranker/issues
Project-URL: Source, https://github.com/document-analysis/zda-content-ranker
Author-email: mohammadraziei <mohammadraziei1375@gmail.com>
License-Expression: MIT
Classifier: Development Status :: 4 - Beta
Classifier: Programming Language :: Python
Classifier: Programming Language :: Python :: Implementation :: CPython
Classifier: Programming Language :: Python :: Implementation :: PyPy
Requires-Python: >=3.7
Requires-Dist: beautifulsoup4
Requires-Dist: elasticsearch
Requires-Dist: markupsafe
Requires-Dist: numpy
Requires-Dist: pandas
Requires-Dist: python-json-logger
Requires-Dist: regex
Requires-Dist: requests
Requires-Dist: selectolax
Requires-Dist: torch
Provides-Extra: rest
Requires-Dist: flask; extra == 'rest'
Requires-Dist: flask-log-request-id; extra == 'rest'
Requires-Dist: flask-restx; extra == 'rest'
Provides-Extra: test
Requires-Dist: pytest; extra == 'test'
